nanologger/__init__.py
nanologger-1.0.3.dist-info/LICENCE.md
nanologger-1.0.3.dist-info/METADATA
nanologger-1.0.3.dist-info/WHEEL
nanologger-1.0.3.dist-info/top_level.txt
nanologger-1.0.3.dist-info/RECORD
