Metadata-Version: 2.1
Name: nanologger
Version: 1.0.3
Summary: A tiny logger tool for Python
Home-page: UNKNOWN
Author: frogstair
Author-email: daniladudkin412@gmail.com
License: UNKNOWN
Platform: UNKNOWN
Classifier: Programming Language :: Python :: 3
Classifier: License :: OSI Approved :: MIT License
Classifier: Operating System :: OS Independent
